Lab_3419/__init__.py
Lab_3419-1.0.2.dist-info/LICENSE
Lab_3419-1.0.2.dist-info/METADATA
Lab_3419-1.0.2.dist-info/WHEEL
Lab_3419-1.0.2.dist-info/top_level.txt
Lab_3419-1.0.2.dist-info/RECORD
