Metadata-Version: 2.1
Name: Lab-3419
Version: 1.0.2
Summary: Lab_3419 is a cross-platform python library
Author-email: Subhendu Das <subhendudas.sinp@gmail.com>
License: MIT License
Classifier: Programming Language :: Python :: 3
Classifier: License :: OSI Approved :: MIT License
Classifier: Operating System :: OS Independent
Requires-Python: >=3.6
License-File: LICENSE
